nico/__init__.py
nico/admin.py
nico/apps.py
nico/models.py
nico/tests.py
nico/views.py
nico/migrations/__init__.py
django_nico-0.15.dist-info/LICENSE
django_nico-0.15.dist-info/METADATA
django_nico-0.15.dist-info/WHEEL
django_nico-0.15.dist-info/top_level.txt
django_nico-0.15.dist-info/RECORD
